<?xml version="1.0" encoding="UTF-8"?>
<tournees xmlns:xs="http://www.w3.org/2001/XMLSchema-instance" xs:noNamespaceSchemaLocation="greenBin.xsd">
  <tournee id="1">
    <zone>Sfax centre</zone>
    <ouvriers>
      <ouvrier id="5"></ouvrier>
    </ouvriers>
    <vehicule id="3"></vehicule>
    <date>2024-06-15</date>
  </tournee>
  <tournee id="2">
    <zone>Sakiet Ezzit</zone>
    <ouvriers>
      <ouvrier id="2"></ouvrier>
      <ouvrier id="3"></ouvrier>
    </ouvriers>
    <vehicule id="2"></vehicule>
    <date>2024-06-15</date>
  </tournee>
  <tournee id="3">
    <zone>sakiet ezzit</zone>
    <ouvriers>
      <ouvrier id="4"></ouvrier>
      <ouvrier id="5"></ouvrier>
    </ouvriers>
    <vehicule id="1"></vehicule>
    <date>2027-12-24</date>
  </tournee>
  <tournee id="4">
    <zone>sakiet ezzit</zone>
    <ouvriers>
      <ouvrier id="4"></ouvrier>
      <ouvrier id="5"></ouvrier>
    </ouvriers>
    <vehicule id="1"></vehicule>
    <date>2027-12-24</date>
  </tournee>
  <tournee id="5">
    <zone>Sfax centre</zone>
    <ouvriers>
      <ouvrier id="4"></ouvrier>
    </ouvriers>
    <vehicule id="1"></vehicule>
    <date>2025-12-13</date>
  </tournee>
</tournees>
